{"2026-04-27":[{"type":"2-bed","bath":"2","rent":2800,"sqft":799,"psf":3.5,"note":"Unit 617"},{"type":"2-bed+den","bath":"2","rent":2900,"sqft":999,"psf":2.9,"note":"Unit 705"},{"type":"1-bed","bath":"1","rent":2250,"sqft":699,"psf":3.22,"note":"Unit 1801"},{"type":"2-bed","bath":"2","rent":2750,"sqft":799,"psf":3.44,"note":"Unit 2103"},{"type":"2-bed","bath":"2","rent":2850,"sqft":999,"psf":2.85,"note":"Unit 515"}],"2026-05-04":[{"type":"2-bed","bath":"2","rent":2800,"sqft":799,"psf":3.5,"note":"Unit 617"},{"type":"2-bed","bath":"2","rent":2750,"sqft":799,"psf":3.44,"note":"Unit 2103"},{"type":"2-bed+den","bath":"2","rent":2900,"sqft":999,"psf":2.9,"note":"Unit 705"},{"type":"2-bed","bath":"2","rent":2850,"sqft":999,"psf":2.85,"note":"Unit 515"}],"2026-05-11":[{"type":"2-bed","bath":"2","rent":2690,"sqft":749,"psf":3.59,"note":"Unit 2103"},{"type":"2-bed+den","bath":"2","rent":2900,"sqft":999,"psf":2.9,"note":"Unit 705"},{"type":"2-bed","bath":"2","rent":2850,"sqft":999,"psf":2.85,"note":"Unit 515"},{"type":"1-bed+den","bath":"1","rent":2100,"sqft":649,"psf":3.24,"note":"Unit 2019"},{"type":"2-bed+den","bath":"2","rent":2900,"sqft":899,"psf":3.23,"note":"Unit 1716"}],"2026-05-19":[{"type":"2-bed","bath":"2","rent":2700,"sqft":799,"psf":3.38,"note":"Unit 617, Floor 6"},{"type":"2-bed+den","bath":"2","rent":2900,"sqft":899,"psf":3.23,"note":"Unit 1716, Floor 17"},{"type":"2-bed","bath":"2","rent":2850,"sqft":999,"psf":2.85,"note":"Unit 515, Floor 5"},{"type":"2-bed+den","bath":"2","rent":2900,"sqft":999,"psf":2.9,"note":"Unit 705, Floor 7"},{"type":"2-bed","bath":"2","rent":2690,"sqft":799,"psf":3.37,"note":"Unit 2103, Floor 21"}],"2026-05-25":[{"type":"2-bed+den","bath":"2","rent":2900,"sqft":899,"psf":3.23,"note":"Unit 1716, Floor 17"},{"type":"2-bed","bath":"2","rent":2700,"sqft":749,"psf":3.6,"note":"Unit 617, Floor 6"},{"type":"2-bed","bath":"2","rent":2850,"sqft":999,"psf":2.85,"note":"Unit 515, Floor 5"},{"type":"2-bed","bath":"2","rent":2690,"sqft":749,"psf":3.59,"note":"Unit 2103, Floor 21"},{"type":"2-bed+den","bath":"2","rent":2900,"sqft":999,"psf":2.9,"note":"Unit 705, Floor 7"}],"2026-06-01":[{"type":"2-bed","bath":"2","rent":2690,"sqft":799,"psf":3.37,"note":"Unit 2103, Floor 21"},{"type":"2-bed+den","bath":"2","rent":3000,"sqft":999,"psf":3.0,"note":"Unit 2506, Floor 25"},{"type":"2-bed","bath":"2","rent":2850,"sqft":999,"psf":2.85,"note":"Unit 515, Floor 5"},{"type":"2-bed","bath":"2","rent":2700,"sqft":799,"psf":3.38,"note":"Unit 617, Floor 6"},{"type":"2-bed+den","bath":"2","rent":2900,"sqft":999,"psf":2.9,"note":"Unit 705, Floor 7"}],"2026-06-08":[{"type":"2-bed","bath":"2","rent":2700,"sqft":799,"psf":3.38,"note":"Unit 617, Floor 6"},{"type":"2-bed","bath":"2","rent":2850,"sqft":999,"psf":2.85,"note":"Unit 515, Floor 5"},{"type":"2-bed","bath":"2","rent":2690,"sqft":799,"psf":3.37,"note":"Unit 2103, Floor 21"},{"type":"2-bed+den","bath":"2","rent":3000,"sqft":999,"psf":3.0,"note":"Unit 2506, Floor 25"}],"2026-06-15":[{"type":"2-bed","bath":"2","rent":2700,"sqft":799,"psf":3.38,"note":"Unit 617, Floor 6"},{"type":"2-bed+den","bath":"2","rent":2900,"sqft":999,"psf":2.9,"note":"Unit 2506, Floor 25"},{"type":"2-bed","bath":"2","rent":2690,"sqft":799,"psf":3.37,"note":"Unit 2103, Floor 21"},{"type":"2-bed","bath":"2","rent":2850,"sqft":999,"psf":2.85,"note":"Unit 515, Floor 5"}]}